fastapi_authorization/__init__.py
fastapi_authorization/abac.py
fastapi_authorization/rbac.py
fastapi_authorization/testing.py
fastapi_authorization/utils.py
fastapi_authorization-0.1.0.dist-info/LICENSE
fastapi_authorization-0.1.0.dist-info/METADATA
fastapi_authorization-0.1.0.dist-info/WHEEL
fastapi_authorization-0.1.0.dist-info/top_level.txt
fastapi_authorization-0.1.0.dist-info/RECORD
