Metadata-Version: 2.1
Name: fastapi-authorization
Version: 0.1.0
Summary: Opinionated authorization package for FastAPI! :tada:
Home-page: https://github.com/Kludex/fastapi-authorization
Author: Marcelo Trylesinski
Author-email: marcelotryle@gmail.com
License: MIT
Platform: UNKNOWN
Classifier: License :: OSI Approved :: MIT License
Classifier: Programming Language :: Python :: 3
Classifier: Programming Language :: Python :: 3 :: Only
Classifier: Programming Language :: Python :: 3.8
Classifier: Programming Language :: Python :: 3.9
Classifier: Programming Language :: Python :: 3.10
Classifier: Programming Language :: Python :: Implementation :: CPython
Requires-Python: >=3.8.0
License-File: LICENSE
Requires-Dist: fastapi (>=0.65.2)
